<annotation>
	<folder>cam3_2024-01-03-15-04-56-243543</folder>
	<filename>20 (10).jpg</filename>
	<path>D:\1My_Scripts\cam3_2024-01-03-15-04-56-243543\20 (10).jpg</path>
	<source>
		<database>Unknown</database>
	</source>
	<size>
		<width>1024</width>
		<height>720</height>
		<depth>3</depth>
	</size>
	<segmented>0</segmented>
	<object>
		<name>g_bottom</name>
		<pose>Unspecified</pose>
		<truncated>0</truncated>
		<difficult>0</difficult>
		<bndbox>
			<xmin>76</xmin>
			<ymin>366</ymin>
			<xmax>572</xmax>
			<ymax>629</ymax>
		</bndbox>
	</object>
	<object>
		<name>price</name>
		<pose>Unspecified</pose>
		<truncated>0</truncated>
		<difficult>0</difficult>
		<bndbox>
			<xmin>80</xmin>
			<ymin>424</ymin>
			<xmax>175</xmax>
			<ymax>497</ymax>
		</bndbox>
	</object>
	<object>
		<name>g_label</name>
		<pose>Unspecified</pose>
		<truncated>0</truncated>
		<difficult>0</difficult>
		<bndbox>
			<xmin>90</xmin>
			<ymin>499</ymin>
			<xmax>448</xmax>
			<ymax>607</ymax>
		</bndbox>
	</object>
	<object>
		<name>ng_lmiter</name>
		<pose>Unspecified</pose>
		<truncated>0</truncated>
		<difficult>0</difficult>
		<bndbox>
			<xmin>572</xmin>
			<ymin>430</ymin>
			<xmax>659</xmax>
			<ymax>567</ymax>
		</bndbox>
	</object>
	<object>
		<name>g_lmiter</name>
		<pose>Unspecified</pose>
		<truncated>0</truncated>
		<difficult>0</difficult>
		<bndbox>
			<xmin>755</xmin>
			<ymin>270</ymin>
			<xmax>850</xmax>
			<ymax>344</ymax>
		</bndbox>
	</object>
	<object>
		<name>g_lmiter</name>
		<pose>Unspecified</pose>
		<truncated>0</truncated>
		<difficult>0</difficult>
		<bndbox>
			<xmin>851</xmin>
			<ymin>204</ymin>
			<xmax>936</xmax>
			<ymax>269</ymax>
		</bndbox>
	</object>
	<object>
		<name>g_miter</name>
		<pose>Unspecified</pose>
		<truncated>0</truncated>
		<difficult>0</difficult>
		<bndbox>
			<xmin>939</xmin>
			<ymin>167</ymin>
			<xmax>990</xmax>
			<ymax>207</ymax>
		</bndbox>
	</object>
</annotation>
