<annotation>
	<folder>reversed_defects</folder>
	<filename>50.jpg</filename>
	<path>D:\annotation_data\Defected_data_capturing\reversed_defects\50.jpg</path>
	<source>
		<database>Unknown</database>
	</source>
	<size>
		<width>1024</width>
		<height>720</height>
		<depth>3</depth>
	</size>
	<segmented>0</segmented>
	<object>
		<name>g_bottom</name>
		<pose>Unspecified</pose>
		<truncated>0</truncated>
		<difficult>0</difficult>
		<bndbox>
			<xmin>21</xmin>
			<ymin>369</ymin>
			<xmax>523</xmax>
			<ymax>634</ymax>
		</bndbox>
	</object>
	<object>
		<name>price</name>
		<pose>Unspecified</pose>
		<truncated>0</truncated>
		<difficult>0</difficult>
		<bndbox>
			<xmin>27</xmin>
			<ymin>419</ymin>
			<xmax>117</xmax>
			<ymax>489</ymax>
		</bndbox>
	</object>
	<object>
		<name>g_label</name>
		<pose>Unspecified</pose>
		<truncated>0</truncated>
		<difficult>0</difficult>
		<bndbox>
			<xmin>30</xmin>
			<ymin>490</ymin>
			<xmax>383</xmax>
			<ymax>598</ymax>
		</bndbox>
	</object>
	<object>
		<name>ng_lmiter</name>
		<pose>Unspecified</pose>
		<truncated>0</truncated>
		<difficult>0</difficult>
		<bndbox>
			<xmin>525</xmin>
			<ymin>458</ymin>
			<xmax>602</xmax>
			<ymax>539</ymax>
		</bndbox>
	</object>
	<object>
		<name>g_miter</name>
		<pose>Unspecified</pose>
		<truncated>0</truncated>
		<difficult>0</difficult>
		<bndbox>
			<xmin>883</xmin>
			<ymin>174</ymin>
			<xmax>929</xmax>
			<ymax>205</ymax>
		</bndbox>
	</object>
	<object>
		<name>ng_lmiter</name>
		<pose>Unspecified</pose>
		<truncated>0</truncated>
		<difficult>0</difficult>
		<bndbox>
			<xmin>802</xmin>
			<ymin>217</ymin>
			<xmax>883</xmax>
			<ymax>277</ymax>
		</bndbox>
	</object>
	<object>
		<name>ng_lmiter</name>
		<pose>Unspecified</pose>
		<truncated>0</truncated>
		<difficult>0</difficult>
		<bndbox>
			<xmin>727</xmin>
			<ymin>275</ymin>
			<xmax>798</xmax>
			<ymax>333</ymax>
		</bndbox>
	</object>
	<object>
		<name>ng_lmiter</name>
		<pose>Unspecified</pose>
		<truncated>0</truncated>
		<difficult>0</difficult>
		<bndbox>
			<xmin>601</xmin>
			<ymin>385</ymin>
			<xmax>676</xmax>
			<ymax>454</ymax>
		</bndbox>
	</object>
</annotation>
